LICENSE
MANIFEST.in
README.md
setup.cfg
setup.py
src/sentry_gitlab/__init__.py
src/sentry_gitlab/plugin.py
src/sentry_gitlab.egg-info/PKG-INFO
src/sentry_gitlab.egg-info/SOURCES.txt
src/sentry_gitlab.egg-info/dependency_links.txt
src/sentry_gitlab.egg-info/entry_points.txt
src/sentry_gitlab.egg-info/not-zip-safe
src/sentry_gitlab.egg-info/requires.txt
src/sentry_gitlab.egg-info/top_level.txt