Metadata-Version: 1.1
Name: sentry-gitlab
Version: 0.2.0
Summary: A Sentry extension which integrates with GitLab.
Home-page: http://github.com/ajcrowe/sentry-gitlab
Author: Alex Crowe
Author-email: alex@pancentric.com
License: BSD
Platform: UNKNOWN
Classifier: Framework :: Django
Classifier: Intended Audience :: Developers
Classifier: Intended Audience :: System Administrators
Classifier: Operating System :: OS Independent
Classifier: Topic :: Software Development
